{
   "Type": "CustomFarming.simpleMachine",
   "Name": "Dye Mixer",
   "Description": "Mixes dye with other products to produce goods with vibrant colors.",
   "Tilesheet" : "DyeMixer.png",
   "TileIndex" : 0,
   "WorkAnimationFrames" : 3,
   "ReadyTileIndex" : 4,
   "AnimationSpeed" : 85,
   "CategoryName" : "Crafting",
   "Materials" : [1049,428,1043,330],
   "RequieredStack" : 3,
   "StarterMaterial" : 1050,
   "StarterMaterialStack" : 2,
   "Crafting" : "334 5 338 2 787 1 335 2",
   "Produce": {
      "Name": "Colored Cloth",
      "Description": "A vibrantly colored object made with natural dye.",
	  "usePrefix" : false,
	  "useSuffix" : false,
	  "useColor" : false,
	  "ProduceID" : 1054,
	  "Stack" : 3,
	  "ProductionTime" : 120,
   },
   "SpecialProduce" : 	[
	  {
	  "Material" : 1049,
	  "ProduceID" : 1035,
	  "Name": "Soy Ink",
      },
      {
	  "Material" : 1043,
	  "ProduceID" : 1052,
	  "Name": "Colored Paper",
      },
	  {
	  "Material" : 330,
	  "ProduceID" : 1054,
	  "Name": "Colored Clay",
	  },
	  	  
	  ]   
}
